lispy/__init__.py
lispy/core_meta_functions.lpy
lispy/tools.lpy
lispy/core/importer.py
lispy/core/macro.py
lispy/core/meta_functions.py
lispy/core/nodes.py
lispy/core/parser.py
lispy/core/utils.py
lispy/core/compiler/__init__.py
lispy/core/compiler/expr.py
lispy/core/compiler/literal.py
lispy/core/compiler/stmt.py
lispy/core/compiler/utils.py
lispy/macros/__init__.py
lispy/macros/init.lpy
lispy/macros/sugar.lpy
lispython-0.3.2.dist-info/METADATA
lispython-0.3.2.dist-info/WHEEL
lispython-0.3.2.dist-info/entry_points.txt
lispython-0.3.2.dist-info/licenses/LICENSE.md
lispython-0.3.2.dist-info/RECORD
