Metadata-Version: 2.4
Name: lispython
Version: 0.3.2
Summary: Lisp-like Syntax for Python with Lisp-like Macros
Project-URL: Homepage, https://jetack.github.io/lispython
Project-URL: Repository, https://github.com/jetack/lispython
Author-email: Jetack <jetack23@gmail.com>
License: MIT
License-File: LICENSE.md
Requires-Python: >=3.11
Provides-Extra: dev
Requires-Dist: pre-commit>=3.6.0; extra == 'dev'
Requires-Dist: pytest>=8.0.0; extra == 'dev'
Requires-Dist: ruff>=0.8.0; extra == 'dev'
Requires-Dist: toml>=0.10.2; extra == 'dev'
Provides-Extra: docs
Requires-Dist: mike>=2.1.3; extra == 'docs'
Requires-Dist: mkdocs-macros-plugin>=1.3.7; extra == 'docs'
Requires-Dist: mkdocs-material>=9.6.14; extra == 'docs'
